__init__.py
archinit/__init__.py
archinit/main.py
archinit-0.1.0.dist-info/licenses/LICENSE
archinit-0.1.0.dist-info/METADATA
archinit-0.1.0.dist-info/WHEEL
archinit-0.1.0.dist-info/entry_points.txt
archinit-0.1.0.dist-info/top_level.txt
archinit-0.1.0.dist-info/RECORD
