Metadata-Version: 2.4
Name: archinit
Version: 0.1.0
Summary: cli tool for generating clean architecture project structure
Author-email: Lev <leofisherking@gmail.com>
License: GPLv3
Project-URL: telegram, https://t.me/gabellum
Requires-Python: >=3.8
License-File: LICENSE
Requires-Dist: build>=1.2.2.post1
Requires-Dist: twine>=6.1.0
Requires-Dist: typer>=0.16.0
Dynamic: license-file
